{
  "60_days": {
    "trades": 27,
    "win_rate": 55.56,
    "loss_rate": 44.44,
    "profit_factor": 2.53,
    "avg_win": 2133.49,
    "avg_loss": -1052.7,
    "net_return": 129.13,
    "cagr": 3153.61,
    "max_dd": -16.05,
    "sharpe": 3.715,
    "sortino": 13.242,
    "calmar": 196.53,
    "final_cap": 34369.91
  },
  "120_days": {
    "trades": 4,
    "win_rate": 25.0,
    "loss_rate": 75.0,
    "profit_factor": 0.43,
    "avg_win": 1451.75,
    "avg_loss": -1123.78,
    "net_return": -12.8,
    "cagr": -24.99,
    "max_dd": -20.49,
    "sharpe": -1.124,
    "sortino": -3.713,
    "calmar": -1.22,
    "final_cap": 13080.41
  },
  "8_years": {
    "trades": 16,
    "win_rate": 31.25,
    "loss_rate": 68.75,
    "profit_factor": 0.89,
    "avg_win": 1652.4,
    "avg_loss": -839.35,
    "net_return": -6.47,
    "cagr": -0.62,
    "max_dd": -24.82,
    "sharpe": -0.003,
    "sortino": -0.001,
    "calmar": -0.025,
    "final_cap": 14029.18
  },
  "Walk_Forward": {
    "Fold_1": {
      "trades": 16,
      "win_rate": 31.25,
      "loss_rate": 68.75,
      "profit_factor": 0.89,
      "avg_win": 1652.4,
      "avg_loss": -839.35,
      "net_return": -6.47,
      "cagr": -6.47,
      "max_dd": -24.82,
      "sharpe": -0.009,
      "sortino": -0.009,
      "calmar": -0.261,
      "final_cap": 14029.18,
      "start_date": "2015-01-09",
      "end_date": "2016-01-18"
    },
    "Fold_2": {
      "trades": 27,
      "win_rate": 48.15,
      "loss_rate": 51.85,
      "profit_factor": 1.31,
      "avg_win": 1390.59,
      "avg_loss": -983.01,
      "net_return": 28.77,
      "cagr": 28.77,
      "max_dd": -22.53,
      "sharpe": 0.874,
      "sortino": 1.135,
      "calmar": 1.277,
      "final_cap": 19315.55,
      "start_date": "2016-01-19",
      "end_date": "2017-01-25"
    },
    "Fold_3": {
      "trades": 19,
      "win_rate": 42.11,
      "loss_rate": 57.89,
      "profit_factor": 0.6,
      "avg_win": 476.79,
      "avg_loss": -581.17,
      "net_return": -17.19,
      "cagr": -17.19,
      "max_dd": -21.58,
      "sharpe": -0.755,
      "sortino": -0.312,
      "calmar": -0.796,
      "final_cap": 12421.43,
      "start_date": "2017-01-27",
      "end_date": "2018-02-01"
    },
    "Fold_4": {
      "trades": 31,
      "win_rate": 51.61,
      "loss_rate": 48.39,
      "profit_factor": 1.4,
      "avg_win": 1243.76,
      "avg_loss": -948.51,
      "net_return": 37.82,
      "cagr": 37.82,
      "max_dd": -22.54,
      "sharpe": 0.996,
      "sortino": 1.3,
      "calmar": 1.678,
      "final_cap": 20672.45,
      "start_date": "2018-02-02",
      "end_date": "2019-02-11"
    },
    "Fold_5": {
      "trades": 5,
      "win_rate": 40.0,
      "loss_rate": 60.0,
      "profit_factor": 0.17,
      "avg_win": 290.8,
      "avg_loss": -1124.14,
      "net_return": -18.61,
      "cagr": -18.61,
      "max_dd": -21.64,
      "sharpe": -1.42,
      "sortino": -2.482,
      "calmar": -0.86,
      "final_cap": 12209.19,
      "start_date": "2019-02-12",
      "end_date": "2020-02-20"
    },
    "Fold_6": {
      "trades": 3,
      "win_rate": 0.0,
      "loss_rate": 100.0,
      "profit_factor": 0.0,
      "avg_win": 0.0,
      "avg_loss": -1123.78,
      "net_return": -22.48,
      "cagr": -22.48,
      "max_dd": -16.2,
      "sharpe": -1.419,
      "sortino": -2.985,
      "calmar": -1.388,
      "final_cap": 11628.66,
      "start_date": "2020-02-24",
      "end_date": "2021-02-25"
    },
    "Fold_7": {
      "trades": 6,
      "win_rate": 16.67,
      "loss_rate": 83.33,
      "profit_factor": 0.67,
      "avg_win": 3526.03,
      "avg_loss": -1047.63,
      "net_return": -11.41,
      "cagr": -11.41,
      "max_dd": -23.64,
      "sharpe": -0.275,
      "sortino": -0.504,
      "calmar": -0.483,
      "final_cap": 13287.87,
      "start_date": "2021-02-26",
      "end_date": "2022-03-07"
    },
    "Fold_8": {
      "trades": 3,
      "win_rate": 0.0,
      "loss_rate": 100.0,
      "profit_factor": 0.0,
      "avg_win": 0.0,
      "avg_loss": -1124.5,
      "net_return": -22.49,
      "cagr": -22.49,
      "max_dd": -22.49,
      "sharpe": -1.739,
      "sortino": -2.863,
      "calmar": -1.0,
      "final_cap": 11626.5,
      "start_date": "2022-03-08",
      "end_date": "2023-03-13"
    },
    "Fold_9": {
      "trades": 38,
      "win_rate": 50.0,
      "loss_rate": 50.0,
      "profit_factor": 1.42,
      "avg_win": 1346.76,
      "avg_loss": -947.47,
      "net_return": 50.58,
      "cagr": 50.58,
      "max_dd": -22.73,
      "sharpe": 1.46,
      "sortino": 1.952,
      "calmar": 2.225,
      "final_cap": 22586.5,
      "start_date": "2023-03-14",
      "end_date": "2024-03-19"
    },
    "Fold_10": {
      "trades": 5,
      "win_rate": 40.0,
      "loss_rate": 60.0,
      "profit_factor": 0.53,
      "avg_win": 894.28,
      "avg_loss": -1124.14,
      "net_return": -10.56,
      "cagr": -10.56,
      "max_dd": -20.09,
      "sharpe": -1.394,
      "sortino": -2.669,
      "calmar": -0.526,
      "final_cap": 13416.14,
      "start_date": "2024-03-20",
      "end_date": "2025-03-26"
    },
    "Fold_11": {
      "trades": 4,
      "win_rate": 25.0,
      "loss_rate": 75.0,
      "profit_factor": 0.06,
      "avg_win": 199.13,
      "avg_loss": -1124.5,
      "net_return": -21.16,
      "cagr": -25.45,
      "max_dd": -21.16,
      "sharpe": -1.798,
      "sortino": -3.627,
      "calmar": -1.203,
      "final_cap": 11825.63,
      "start_date": "2025-03-27",
      "end_date": "2026-01-22"
    }
  }
}